extera/__init__.py
extera/api/__init__.py
extera/api/auth.py
extera/api/base.py
extera/api/case.py
extera/api/config.py
extera/api/geometry.py
extera/api/notificationListener.py
extera/api/paramValue.py
extera/api/project.py
extera/api/run.py
extera/api/study.py
extera/tools/__init__.py
extera/tools/interpret.py
extera/utils/__init__.py
extera/utils/excel.py
extera/utils/range.py
extera-1.0.0.2.dist-info/LICENSE.txt
extera-1.0.0.2.dist-info/METADATA
extera-1.0.0.2.dist-info/WHEEL
extera-1.0.0.2.dist-info/entry_points.txt
extera-1.0.0.2.dist-info/top_level.txt
extera-1.0.0.2.dist-info/RECORD
