Metadata-Version: 2.1
Name: extera
Version: 1.0.0.2
Summary: Python language binding for Extera Design API
Author: Extera Design
License: Copyright (c) 2023 Extera Design. All rights reserved.
Classifier: Programming Language :: Python :: 3
Classifier: Operating System :: OS Independent
Classifier: Intended Audience :: Developers
Classifier: Topic :: Scientific/Engineering
Classifier: Topic :: Software Development :: Libraries
Requires-Python: >=3.10
License-File: LICENSE.txt
Requires-Dist: requests
Requires-Dist: websockets
Requires-Dist: lark
Requires-Dist: pandas
Requires-Dist: openpyxl
